neon_lang_plugin_amazon_translate/__init__.py
neon_lang_plugin_amazon_translate-0.1.2.dist-info/LICENSE.md
neon_lang_plugin_amazon_translate-0.1.2.dist-info/METADATA
neon_lang_plugin_amazon_translate-0.1.2.dist-info/WHEEL
neon_lang_plugin_amazon_translate-0.1.2.dist-info/entry_points.txt
neon_lang_plugin_amazon_translate-0.1.2.dist-info/top_level.txt
neon_lang_plugin_amazon_translate-0.1.2.dist-info/zip-safe
neon_lang_plugin_amazon_translate-0.1.2.dist-info/RECORD
