Metadata-Version: 2.1
Name: neon-lang-plugin-amazon-translate
Version: 0.1.2
Summary: Amazon Translate Language Plugin
Home-page: https://github.com/NeonGeckoCom/neon-lang-plugin-amazon_translate
Author: Neongecko
Author-email: developers@neon.ai
License: BSD-3-Clause
Keywords: neon mycroft plugin language detection translation
Platform: UNKNOWN
Classifier: Development Status :: 3 - Alpha
Classifier: Intended Audience :: Developers
Classifier: Topic :: Text Processing :: Linguistic
Classifier: Programming Language :: Python :: 2
Classifier: Programming Language :: Python :: 2.7
Classifier: Programming Language :: Python :: 3
Classifier: Programming Language :: Python :: 3.0
Classifier: Programming Language :: Python :: 3.1
Classifier: Programming Language :: Python :: 3.2
Classifier: Programming Language :: Python :: 3.3
Classifier: Programming Language :: Python :: 3.4
Classifier: Programming Language :: Python :: 3.5
Classifier: Programming Language :: Python :: 3.6
Requires-Dist: ovos-plugin-manager (~=0.0.1)
Requires-Dist: boto3 (~=1.15)
Requires-Dist: SpeechRecognition (~=3.8)
